odoo/addons/product_attribute_value_menu/README.rst
odoo/addons/product_attribute_value_menu/__init__.py
odoo/addons/product_attribute_value_menu/__manifest__.py
odoo/addons/product_attribute_value_menu/i18n/it.po
odoo/addons/product_attribute_value_menu/i18n/product_attribute_value_menu.pot
odoo/addons/product_attribute_value_menu/models/__init__.py
odoo/addons/product_attribute_value_menu/models/product_attribute_value.py
odoo/addons/product_attribute_value_menu/readme/CONFIGURE.rst
odoo/addons/product_attribute_value_menu/readme/CONTRIBUTORS.rst
odoo/addons/product_attribute_value_menu/readme/DESCRIPTION.rst
odoo/addons/product_attribute_value_menu/readme/USAGE.rst
odoo/addons/product_attribute_value_menu/static/description/icon.png
odoo/addons/product_attribute_value_menu/static/description/index.html
odoo/addons/product_attribute_value_menu/views/product_attribute_value_views.xml
odoo/addons/product_attribute_value_menu/views/product_template_attribute_value_views.xml
odoo14_addon_product_attribute_value_menu-14.0.2.0.2.dist-info/METADATA
odoo14_addon_product_attribute_value_menu-14.0.2.0.2.dist-info/WHEEL
odoo14_addon_product_attribute_value_menu-14.0.2.0.2.dist-info/top_level.txt
odoo14_addon_product_attribute_value_menu-14.0.2.0.2.dist-info/RECORD
